MANIFEST.in
README.md
VERSION
exosite.py
setup.py
bin/exosite
exosite.egg-info/PKG-INFO
exosite.egg-info/SOURCES.txt
exosite.egg-info/dependency_links.txt
exosite.egg-info/requires.txt
exosite.egg-info/top_level.txt
test/test_roundtrip.py