Metadata-Version: 1.1
Name: exosite
Version: 0.25
Summary: Command line interface for Exosite Murano.
Home-page: http://exosite.com
Author: Ivan Lan
Author-email: ivanlan@exosite.com
License: UNKNOWN
Keywords: exosite,m2m,iot,cli,murano
Platform: UNKNOWN
Classifier: Development Status :: 5 - Production/Stable
Classifier: Environment :: Console
Classifier: Intended Audience :: Developers
Classifier: Programming Language :: Python
Classifier: Topic :: Software Development :: Build Tools
Classifier: Operating System :: Microsoft :: Windows
Classifier: Operating System :: Unix
Classifier: Operating System :: MacOS
